{
  "state": "new-mexico",
  "stateName": "New Mexico",
  "lastUpdated": "2025-12-26",
  "seo": {
    "title": "Top 25 Marketing Agencies in New Mexico (2025) | Gappsy",
    "meta_description": "Discover New Mexico's best marketing agencies. Comprehensive rankings of top-rated firms serving local businesses across New Mexico.",
    "canonical_url": "https://www.gappsy.com/marketing-agencies-in-new-mexico-united-states/",
    "og_title": "Top 25 Marketing Agencies in New Mexico (2025)",
    "og_description": "Discover New Mexico's best marketing agencies serving businesses across the state.",
    "focus_keyword": "marketing agencies in New Mexico"
  }
}