{
  "state": "ohio",
  "stateName": "Ohio",
  "lastUpdated": "2025-12-26",
  "seo": {
    "title": "Top 25 Marketing Agencies in Ohio (2025) | Gappsy",
    "meta_description": "Discover Ohio's best marketing agencies. Comprehensive rankings of top-rated firms serving local businesses across Ohio.",
    "canonical_url": "https://www.gappsy.com/marketing-agencies-in-ohio-united-states/",
    "og_title": "Top 25 Marketing Agencies in Ohio (2025)",
    "og_description": "Discover Ohio's best marketing agencies serving businesses across the state.",
    "focus_keyword": "marketing agencies in Ohio"
  }
}