[
  {
    "rank": 222,
    "id": "1c0b6aed-6aed-4600-980d-b05aa2cf0ccb",
    "slug": "northflank",
    "name": "Northflank",
    "website": "https://northflank.com",
    "categorySlug": "hosting"
  },
  {
    "rank": 223,
    "id": "46c7eebc-d6a3-4c06-b0fb-74483d16333d",
    "slug": "qovery",
    "name": "Qovery",
    "website": "https://www.qovery.com",
    "categorySlug": "hosting"
  },
  {
    "rank": 224,
    "id": "196d4b7c-1987-4513-97d0-d974741e4db3",
    "slug": "platform-sh",
    "name": "Platform.sh",
    "website": "https://platform.sh",
    "categorySlug": "hosting"
  },
  {
    "rank": 225,
    "id": "4f36c751-0719-4122-8fe0-e1bd976404d2",
    "slug": "cloudways",
    "name": "Cloudways",
    "website": "https://www.cloudways.com",
    "categorySlug": "hosting"
  },
  {
    "rank": 226,
    "id": "a0672926-1230-4fae-8c77-9a1304584c44",
    "slug": "kinsta",
    "name": "Kinsta",
    "website": "https://kinsta.com",
    "categorySlug": "hosting"
  },
  {
    "rank": 227,
    "id": "0ed951ec-77f0-4b46-b0d3-dc10cc9de347",
    "slug": "wp-engine",
    "name": "WP Engine",
    "website": "https://wpengine.com",
    "categorySlug": "hosting"
  },
  {
    "rank": 228,
    "id": "8dd02588-9e72-460d-8c15-9f28eeaf959d",
    "slug": "pantheon",
    "name": "Pantheon",
    "website": "https://pantheon.io",
    "categorySlug": "hosting"
  },
  {
    "rank": 229,
    "id": "8ed72c61-cf6e-4bb5-818c-15ca4c39cc8b",
    "slug": "a2-hosting",
    "name": "A2 Hosting",
    "website": "https://www.a2hosting.com",
    "categorySlug": "hosting"
  },
  {
    "rank": 230,
    "id": "c25e7433-44ad-439d-a4df-0347e6f2e9c2",
    "slug": "hostinger",
    "name": "Hostinger",
    "website": "https://www.hostinger.com",
    "categorySlug": "hosting"
  },
  {
    "rank": 231,
    "id": "fca0329e-c98c-4d5a-847a-38aca9d3e0c4",
    "slug": "siteground",
    "name": "SiteGround",
    "website": "https://www.siteground.com",
    "categorySlug": "hosting"
  }
]