[
  {
    "slug": "cognism-vs-lusha",
    "tool_a_id": "48c4e035-ee4a-4d7c-9e7a-7d9f3a3f6d4e",
    "tool_a_slug": "cognism",
    "tool_a_name": "Cognism",
    "tool_b_id": "cb38ef74-ed67-4950-a546-3ece2c203f18",
    "tool_b_slug": "lusha",
    "tool_b_name": "Lusha"
  },
  {
    "slug": "leadiq-vs-seamless-ai",
    "tool_a_id": "88b216db-d52e-49cb-b940-093f9a2044aa",
    "tool_a_slug": "leadiq",
    "tool_a_name": "LeadIQ",
    "tool_b_id": "c106a3ac-ef7c-4e45-a70c-a482ca2fea51",
    "tool_b_slug": "seamless-ai",
    "tool_b_name": "Seamless.AI"
  },
  {
    "slug": "clay-vs-warmly",
    "tool_a_id": "c5a72856-c532-4882-bce1-c4c3664d929b",
    "tool_a_slug": "clay",
    "tool_a_name": "Clay",
    "tool_b_id": "4acb5d47-918c-44a6-ad53-de5ddb07110f",
    "tool_b_slug": "warmly",
    "tool_b_name": "Warmly"
  },
  {
    "slug": "cal-com-vs-savvycal",
    "tool_a_id": "aee8fc7c-2bc5-4e1a-ba70-2a8958f81cc7",
    "tool_a_slug": "cal-com",
    "tool_a_name": "Cal.com",
    "tool_b_id": "7bb0117d-0174-4a18-963f-a0a873a4b2b1",
    "tool_b_slug": "savvycal",
    "tool_b_name": "SavvyCal"
  },
  {
    "slug": "calday-vs-zencal",
    "tool_a_id": "59765ae5-0390-4cfe-8c3d-77fc6b87aa0d",
    "tool_a_slug": "calday",
    "tool_a_name": "Calday",
    "tool_b_id": "bef9e8d8-86d1-4254-b054-8fdc286672d5",
    "tool_b_slug": "zencal",
    "tool_b_name": "Zencal"
  },
  {
    "slug": "oncehub-vs-youcanbookme",
    "tool_a_id": "bde29d40-4c62-40a8-861e-ba3a8862dedc",
    "tool_a_slug": "oncehub",
    "tool_a_name": "OnceHub",
    "tool_b_id": "523ab821-6dbc-4f0a-ad9c-477f20ab7e52",
    "tool_b_slug": "youcanbookme",
    "tool_b_name": "YouCanBookMe"
  },
  {
    "slug": "doodle-vs-rallly",
    "tool_a_id": "f952f07d-b3f7-4527-af58-4d07608f83cf",
    "tool_a_slug": "doodle",
    "tool_a_name": "Doodle",
    "tool_b_id": "03916389-8c72-4b6c-ac5d-c652f169146c",
    "tool_b_slug": "rallly",
    "tool_b_name": "rallly"
  },
  {
    "slug": "appointlet-vs-setmore",
    "tool_a_id": "1b9d7fb5-074c-4e82-9ac7-0933bc5db0cc",
    "tool_a_slug": "appointlet",
    "tool_a_name": "Appointlet",
    "tool_b_id": "d498e2a2-205f-436a-b281-0d60d3a97b18",
    "tool_b_slug": "setmore",
    "tool_b_name": "Setmore"
  }
]