[
  {
    "rank": 219,
    "id": "2d8087e6-e022-4b9c-9760-d491836887d8",
    "slug": "ant-media-server",
    "name": "Ant Media Server",
    "website": "https://antmedia.io",
    "categorySlug": "media-tools"
  },
  {
    "rank": 220,
    "id": "abc2721a-0a2c-4cbe-a939-ce3315e4592a",
    "slug": "srs",
    "name": "SRS",
    "website": "https://ossrs.io",
    "categorySlug": "media-tools"
  },
  {
    "rank": 221,
    "id": "ba63a23f-3cf0-4180-a7bf-2561af98bb09",
    "slug": "obs-studio",
    "name": "OBS Studio",
    "website": "https://obsproject.com",
    "categorySlug": "media-tools"
  },
  {
    "rank": 222,
    "id": "0b8a01cb-eaf5-4307-9fc0-f73aa6bf0bec",
    "slug": "kdenlive",
    "name": "Kdenlive",
    "website": "https://kdenlive.org",
    "categorySlug": "video-editing"
  },
  {
    "rank": 223,
    "id": "57934454-9221-47e3-87a7-83d5b080c4a6",
    "slug": "shotcut",
    "name": "Shotcut",
    "website": "https://shotcut.org",
    "categorySlug": "video-editing"
  },
  {
    "rank": 224,
    "id": "541442eb-549b-42a3-a8f8-d423bdb42a14",
    "slug": "openshot",
    "name": "OpenShot",
    "website": "https://www.openshot.org",
    "categorySlug": "video-editing"
  },
  {
    "rank": 225,
    "id": "76721f82-dab0-44d8-9e79-1d3b6df99f76",
    "slug": "olive-video-editor",
    "name": "Olive Video Editor",
    "website": "https://www.olivevideoeditor.org",
    "categorySlug": "video-editing"
  },
  {
    "rank": 226,
    "id": "588dad8e-446f-42e3-8554-3bef2ef37a9a",
    "slug": "pitivi",
    "name": "Pitivi",
    "website": "https://www.pitivi.org",
    "categorySlug": "video-editing"
  },
  {
    "rank": 227,
    "id": "5193cb21-ed1a-4efa-8952-c3400dfcbad7",
    "slug": "handbrake",
    "name": "HandBrake",
    "website": "https://handbrake.fr",
    "categorySlug": "video-editing"
  },
  {
    "rank": 228,
    "id": "0feb9ecc-7812-47e0-afb1-c05d828a05c3",
    "slug": "audacity",
    "name": "Audacity",
    "website": "https://www.audacityteam.org",
    "categorySlug": "media-tools"
  }
]